{
  "episodes": [
    { "episode": 1, "link": "https://drive.usercontent.google.com/download?id=1GkJum0wvLQitsE8D17MBFTNtfAk7kIxB&export=download&authuser=0" },
    { "episode": 2, "link": "https://drive.usercontent.google.com/download?id=1sHPd-GaH9_hlkOmotNC6SZZ-3zQxRAAL&export=download&authuser=0" },
    { "episode": 3, "link": "https://drive.usercontent.google.com/download?id=1oKM_SSw3KSWmQJNE1udFp-ySTYkgCz7h&export=download&authuser=0" },
    { "episode": 4, "link": "https://drive.usercontent.google.com/download?id=1oWpoX-7KLSZuO4SRgrnZnl1LgsxbOKqu&export=download&authuser=0" },
    { "episode": 5, "link": "https://drive.usercontent.google.com/download?id=1NH_f3TnA_SCcn7Ws5hyzDSoCvMlQhXA8&export=download&authuser=0" },
    { "episode": 6, "link": "https://drive.usercontent.google.com/download?id=1EnaDNRloEo1JcWftL5JELzHTesXloxF5&export=download&authuser=0" },
    { "episode": 7, "link": "https://drive.usercontent.google.com/download?id=1NA_6sa4FJ2HIacZodGZFEhqwJ_K_8lUj&export=download&authuser=0" },
    { "episode": 8, "link": "https://drive.usercontent.google.com/download?id=1IJYcjfl4YHy_YgbIP4T9EZ88rLXR40mS&export=download&authuser=0" },
    { "episode": 9, "link": "https://drive.usercontent.google.com/download?id=1f2hFG5LXiVtEMHqGfa50G51ZeHZLkKWq&export=download&authuser=0" },
    { "episode": 10, "link": "https://drive.usercontent.google.com/download?id=1il5eGNn92jABGb9t2XL4-jqCT0pqDaAs&export=download&authuser=0" },
    { "episode": 11, "link": "https://drive.usercontent.google.com/download?id=1TJE--AyQWr4BFOqMT8q2zzbdfsqfwj2a&export=download&authuser=0" },
    { "episode": 12, "link": "https://drive.usercontent.google.com/download?id=1hYcUC4aXyDtjSUorUDK9StncFtdfdqnp&export=download&authuser=0" },
    { "episode": 13, "link": "https://drive.usercontent.google.com/download?id=1pLjsyCVItK7D9mIMSpLpf9dTaALdVJwu&export=download&authuser=0" },
    { "episode": 14, "link": "https://drive.usercontent.google.com/download?id=17Jd8G7nxW_hqNiLA0_-jiWdZybo4vztQ&export=download&authuser=0" },
    { "episode": 15, "link": "https://drive.usercontent.google.com/download?id=1T6WeTmVg4fC7KvmIwpXM9y-pTLTVNZre&export=download&authuser=0" },
    { "episode": 16, "link": "https://drive.usercontent.google.com/download?id=1rXpKG3k344nZ2X_w1Jow4fy7Qquhyydp&export=download&authuser=0" },
    { "episode": 17, "link": "https://drive.usercontent.google.com/download?id=1so_uvCmSTlMUxvEzwWs8Cj1er4vwOebA&export=download&authuser=0" },
    { "episode": 18, "link": "https://drive.usercontent.google.com/download?id=1GvaHYmdQaOV8iABSEGDQZi1fsR8yWrAK&export=download&authuser=0" },
    { "episode": 19, "link": "https://drive.usercontent.google.com/download?id=1Zfn8QW0Hpo-7Siq20Gwt91ws0BavCVlB&export=download&authuser=0" },
    { "episode": 20, "link": "https://drive.usercontent.google.com/download?id=18EUMQhNNQ5FJu4P8aXw1_NiZjIIuZVqh&export=download&authuser=0" },
    { "episode": 21, "link": "https://drive.usercontent.google.com/download?id=1K78kROxKfkWmqALbjrH16-0sy2kVgwqe&export=download&authuser=0" },
    { "episode": 22, "link": "https://drive.usercontent.google.com/download?id=1yeVTtpSRoe93zz3Vf5-FGPnL-4o2e1m1&export=download&authuser=0" },
    { "episode": 23, "link": "https://drive.usercontent.google.com/download?id=18FfQ-L9ViVP0FfuXWEdc1A2KwM0xMRoq&export=download&authuser=0" },
    { "episode": 24, "link": "https://drive.usercontent.google.com/download?id=1qiA7O2goTSWNmaL_I6pjgkwYzydDhJ4T&export=download&authuser=0" },
    { "episode": 25, "link": "https://drive.usercontent.google.com/download?id=1nTewXWnLpBsT9uEj786th_HjHjFSISNz&export=download&authuser=0" },
    { "episode": 26, "link": "https://drive.usercontent.google.com/download?id=1PtO0-e2pbPMXF2p56qUIK9Hf1s3ONU5F&export=download&authuser=0" },
    { "episode": 27, "link": "https://drive.usercontent.google.com/download?id=1vaJE2hpQS1lspHAsQl2YX_WtRYOgcpBW&export=download&authuser=0" },
    { "episode": 28, "link": "https://drive.usercontent.google.com/download?id=1BxahwXcpwWbaoiWHn0_gLQYJ_ex1HVqs&export=download&authuser=0" },
    { "episode": 29, "link": "https://drive.usercontent.google.com/download?id=1SC-4jv8Wy50yMt7PZQyOAhfBTgusAc9d&export=download&authuser=0" },
    { "episode": 30, "link": "https://drive.usercontent.google.com/download?id=17sX9IOnggKMbnveoGztDXcmC4na17IkT&export=download&authuser=0" },
    { "episode": 31, "link": "https://drive.usercontent.google.com/download?id=1usP0DROEwpz0KwvL2Ob4Rl-0OVq0ynU3&export=download&authuser=0" },
    { "episode": 32, "link": "https://drive.usercontent.google.com/download?id=1B2KrvouWVBynHP0nsSEFXD4qV_ChZCMI&export=download&authuser=0" },
    { "episode": 33, "link": "https://drive.usercontent.google.com/download?id=1T5L4_SRTvOgk1FxdoPP12NGQ50CP0E1T&export=download&authuser=0" },
    { "episode": 34, "link": "https://drive.usercontent.google.com/download?id=1GJO1jRVrcobfZ5m5ajyYfPSsQk-qX2yK&export=download&authuser=0" },
    { "episode": 35, "link": "https://drive.usercontent.google.com/download?id=1e5ggxY2zC-S-Dbcki_nTWaaE0OXHRHqh&export=download&authuser=0" },
    { "episode": 36, "link": "https://drive.usercontent.google.com/download?id=1Q92NbfiBr02JxiMbjy0jZNglJ8kpBwet&export=download&authuser=0" },
    { "episode": 37, "link": "https://drive.usercontent.google.com/download?id=1I7R4x8SZ83wKP_i2_MxqNlJCeFGA85Ae&export=download&authuser=0" },
    { "episode": 38, "link": "https://drive.usercontent.google.com/download?id=1LuehaeJespFMBRzt9Or1t3Zmp3O5I5Jc&export=download&authuser=0" },
    { "episode": 39, "link": "https://drive.usercontent.google.com/download?id=13ziIM9s0d1W9c_VV_wFcjzPin7GKHQ_L&export=download&authuser=0" },
    { "episode": 40, "link": "https://drive.usercontent.google.com/download?id=1aVazp-4vVX-DijCnMYTi7GCVRMYynqiP&export=download&authuser=0" },
    { "episode": 41, "link": "https://drive.usercontent.google.com/download?id=1TCdwqPkogGHOAUK_zrbIykaQDaL7og9K&export=download&authuser=0" },
    { "episode": 42, "link": "https://drive.usercontent.google.com/download?id=1fCsVou9OWvzt14Hmq9QxppKEqTSg5yCs&export=download&authuser=0" },
    { "episode": 43, "link": "https://drive.usercontent.google.com/download?id=1T5L4_SRTvOgk1FxdoPP12NGQ50CP0E1T&export=download&authuser=0" },
    { "episode": 44, "link": "https://drive.usercontent.google.com/download?id=1e5ggxY2zC-S-Dbcki_nTWaaE0OXHRHqh&export=download&authuser=0" },
    { "episode": 45, "link": "https://drive.usercontent.google.com/download?id=1gTdyvOAVk-ucGbF8N0fbXfRUQ6ipRaHw&export=download&authuser=0" },
    { "episode": 46, "link": "https://drive.usercontent.google.com/download?id=1s6nx8RCU_H0eBvWDiVUJIGINNt-Zy8_S&export=download&authuser=0" },
    { "episode": 47, "link": "https://drive.usercontent.google.com/download?id=1kChpjct2WUunLmJj-pxKCZJQ0F5_aOBQ&export=download&authuser=0" },
    { "episode": 48, "link": "https://drive.usercontent.google.com/download?id=1xDotZ3jsd5SMdnPoI-HhmFLR2AEAuYUY&export=download&authuser=0" }
  ]
}
